gdsblenderpy
