Metadata-Version: 2.1
Name: gdsblenderpy
Version: 0.0.3
Summary: GDS to Blender Python Translator
Home-page: https://github.com/matthewvanniekerk/gds-blender-py
Author: Matthew van Niekerk
Author-email: matthewvanniekerk@mac.com
License: UNKNOWN
Platform: UNKNOWN
Classifier: Programming Language :: Python :: 3
Classifier: License :: OSI Approved :: MIT License
Classifier: Operating System :: OS Independent
